search/__main__.py
search/search.py
pgn_filter-0.1.7.dist-info/LICENSE
pgn_filter-0.1.7.dist-info/METADATA
pgn_filter-0.1.7.dist-info/WHEEL
pgn_filter-0.1.7.dist-info/entry_points.txt
pgn_filter-0.1.7.dist-info/top_level.txt
pgn_filter-0.1.7.dist-info/RECORD
